dynamixel_py/__init__.py
dynamixel_py/dynamixel_control_tables.py
dynamixel_py/dynamixel_handler.py
dynamixel_py/servo_group.py
dynamixel_py/utilities.py
dynamixel_py-0.0.5.dist-info/licenses/LICENSE.txt
dynamixel_py-0.0.5.dist-info/METADATA
dynamixel_py-0.0.5.dist-info/WHEEL
dynamixel_py-0.0.5.dist-info/top_level.txt
dynamixel_py-0.0.5.dist-info/RECORD
