Metadata-Version: 2.4
Name: dynamixel_py
Version: 0.0.5
Summary: A python library to control dynamixel servo motors
Author-email: Rohit Thampy <rohitthampy808@gmail.com>
Project-URL: Homepage, https://github.com/rohitthampy/dynamixel_py
Project-URL: Issues, https://github.com/rohitthampy/dynamixel_py/issues
Classifier: Programming Language :: Python :: 3
Classifier: Programming Language :: Python :: 3.8
Classifier: Programming Language :: Python :: 3.9
Classifier: Programming Language :: Python :: 3.10
Classifier: Operating System :: OS Independent
Classifier: License :: OSI Approved :: Apache Software License
Requires-Python: >=3.8
License-File: LICENSE.txt
Requires-Dist: dynamixel-sdk
Dynamic: license-file
